[
  {"a": 12, "b": 67},
  {"a": 89, "b": 59},
  {"a": 18, "b": 17},
  {"a": 99, "b": 87},
  {"a": 92, "b": 10},
  {"a": 86, "b": 69},
  {"a": 45, "b": 65},
  {"a": 60, "b": 88},
  {"a": 33, "b": 62},
  {"a": 49, "b": 61},
  {"a": 61, "b": 14},
  {"a": 89, "b": 84},
  {"a": 89, "b": 61},
  {"a": 86, "b": 51},
  {"a": 20, "b": 94},
  {"a": 92, "b": 57},
  {"a": 42, "b": 37},
  {"a": 93, "b": 47},
  {"a": 55, "b": 88},
  {"a": 20, "b": 96},
  {"a": 19, "b": 19},
  {"a": 84, "b": 73},
  {"a": 17, "b": 85},
  {"a": 44, "b": 60},
  {"a": 96, "b": 39},
  {"a": 38, "b": 83},
  {"a": 45, "b": 37},
  {"a": 21, "b": 60},
  {"a": 76, "b": 42},
  {"a": 10, "b": 23},
  {"a": 37, "b": 67},
  {"a": 20, "b": 48},
  {"a": 37, "b": 99},
  {"a": 14, "b": 13},
  {"a": 10, "b": 68},
  {"a": 47, "b": 44},
  {"a": 94, "b": 70},
  {"a": 23, "b": 38},
  {"a": 55, "b": 24},
  {"a": 75, "b": 57},
  {"a": 34, "b": 12},
  {"a": 80, "b": 62},
  {"a": 27, "b": 14},
  {"a": 53, "b": 88},
  {"a": 35, "b": 19},
  {"a": 68, "b": 12},
  {"a": 56, "b": 72},
  {"a": 45, "b": 24},
  {"a": 45, "b": 38},
  {"a": 28, "b": 28},
  {"a": 55, "b": 19},
  {"a": 76, "b": 34},
  {"a": 46, "b": 58},
  {"a": 82, "b": 66},
  {"a": 74, "b": 11},
  {"a": 85, "b": 39},
  {"a": 69, "b": 12},
  {"a": 67, "b": 63},
  {"a": 47, "b": 69},
  {"a": 56, "b": 67},
  {"a": 88, "b": 55},
  {"a": 19, "b": 33},
  {"a": 72, "b": 34},
  {"a": 18, "b": 10},
  {"a": 28, "b": 56},
  {"a": 92, "b": 48},
  {"a": 36, "b": 36},
  {"a": 93, "b": 10},
  {"a": 80, "b": 57},
  {"a": 44, "b": 33},
  {"a": 38, "b": 92},
  {"a": 93, "b": 29},
  {"a": 51, "b": 58},
  {"a": 11, "b": 33},
  {"a": 74, "b": 92},
  {"a": 87, "b": 81},
  {"a": 89, "b": 76},
  {"a": 50, "b": 83},
  {"a": 76, "b": 42},
  {"a": 30, "b": 72},
  {"a": 34, "b": 24},
  {"a": 71, "b": 47},
  {"a": 66, "b": 63},
  {"a": 20, "b": 29},
  {"a": 38, "b": 50},
  {"a": 53, "b": 23},
  {"a": 50, "b": 98},
  {"a": 10, "b": 48},
  {"a": 52, "b": 60},
  {"a": 57, "b": 57},
  {"a": 93, "b": 20},
  {"a": 21, "b": 18},
  {"a": 51, "b": 90},
  {"a": 74, "b": 96},
  {"a": 95, "b": 64},
  {"a": 49, "b": 21},
  {"a": 63, "b": 51},
  {"a": 40, "b": 75},
  {"a": 38, "b": 15},
  {"a": 65, "b": 76}
]